open_amazon_chat_completions_server/__init__.py
open_amazon_chat_completions_server/main.py
open_amazon_chat_completions_server/adapters/__init__.py
open_amazon_chat_completions_server/adapters/base_adapter.py
open_amazon_chat_completions_server/adapters/bedrock_to_openai_adapter.py
open_amazon_chat_completions_server/adapters/openai_adapter.py
open_amazon_chat_completions_server/adapters/bedrock/__init__.py
open_amazon_chat_completions_server/adapters/bedrock/ai21_strategy.py
open_amazon_chat_completions_server/adapters/bedrock/bedrock_adapter.py
open_amazon_chat_completions_server/adapters/bedrock/bedrock_adapter_strategy_abc.py
open_amazon_chat_completions_server/adapters/bedrock/bedrock_models.py
open_amazon_chat_completions_server/adapters/bedrock/claude_strategy.py
open_amazon_chat_completions_server/adapters/bedrock/cohere_strategy.py
open_amazon_chat_completions_server/adapters/bedrock/meta_strategy.py
open_amazon_chat_completions_server/adapters/bedrock/mistral_strategy.py
open_amazon_chat_completions_server/adapters/bedrock/nova_strategy.py
open_amazon_chat_completions_server/adapters/bedrock/stability_strategy.py
open_amazon_chat_completions_server/adapters/bedrock/titan_strategy.py
open_amazon_chat_completions_server/adapters/bedrock/writer_strategy.py
open_amazon_chat_completions_server/api/__init__.py
open_amazon_chat_completions_server/api/app.py
open_amazon_chat_completions_server/api/errors.py
open_amazon_chat_completions_server/api/dependencies/__init__.py
open_amazon_chat_completions_server/api/dependencies/services.py
open_amazon_chat_completions_server/api/middleware/__init__.py
open_amazon_chat_completions_server/api/middleware/auth.py
open_amazon_chat_completions_server/api/middleware/logging.py
open_amazon_chat_completions_server/api/routes/__init__.py
open_amazon_chat_completions_server/api/routes/chat.py
open_amazon_chat_completions_server/api/routes/files.py
open_amazon_chat_completions_server/api/routes/health.py
open_amazon_chat_completions_server-1.0.2.dist-info/licenses/LICENSE
open_amazon_chat_completions_server-1.0.2.dist-info/METADATA
open_amazon_chat_completions_server-1.0.2.dist-info/WHEEL
open_amazon_chat_completions_server-1.0.2.dist-info/entry_points.txt
open_amazon_chat_completions_server-1.0.2.dist-info/top_level.txt
open_amazon_chat_completions_server-1.0.2.dist-info/RECORD
