Metadata-Version: 2.4
Name: open_amazon_chat_completions_server
Version: 1.0.2
Summary: A server and CLI for interacting between OpenAI and Amazon Bedrock.
Author-email: Danny Teller <danny.teller.io@gmail.com>
Maintainer-email: Danny Teller <danny.teller.io@gmail.com>
License: MIT
Project-URL: Homepage, https://github.com/teabranch/open-amazon-chat-completions-server
Project-URL: Bug Tracker, https://github.com/teabranch/open-amazon-chat-completions-server/issues
Project-URL: Documentation, https://github.com/teabranch/open-amazon-chat-completions-server#readme
Keywords: llm,chatbot,openai,aws,bedrock,chat,api,cli,fastapi
Classifier: Development Status :: 3 - Alpha
Classifier: Intended Audience :: Developers
Classifier: License :: OSI Approved :: MIT License
Classifier: Programming Language :: Python :: 3.12
Classifier: Topic :: Communications :: Chat
Classifier: Topic :: Internet :: WWW/HTTP :: WSGI :: Application
Classifier: Topic :: Scientific/Engineering :: Artificial Intelligence
Classifier: Topic :: Software Development :: Libraries :: Python Modules
Classifier: Topic :: Utilities
Requires-Python: >=3.12
License-File: LICENSE
Requires-Dist: fastapi>=0.110.0
Requires-Dist: uvicorn[standard]>=0.20.0
Requires-Dist: click>=8.0.0
Requires-Dist: requests>=2.25.0
Requires-Dist: rich>=13.0.0
Requires-Dist: python-dotenv>=0.20.0
Requires-Dist: python-multipart>=0.0.6
Requires-Dist: openai>=1.0.0
Requires-Dist: boto3>=1.28.0
Requires-Dist: tenacity>=8.2.0
Provides-Extra: dev
Requires-Dist: pytest>=8.0.0; extra == "dev"
Requires-Dist: pytest-asyncio>=0.23.0; extra == "dev"
Requires-Dist: pytest-cov>=4.0.0; extra == "dev"
Requires-Dist: httpx>=0.23; extra == "dev"
Requires-Dist: ruff>=0.4.0; extra == "dev"
Requires-Dist: mypy>=1.0.0; extra == "dev"
Dynamic: license-file
